eouTools/__init__.py
eouTools/__main__.py
eouTools/constants.py
eouTools/decorators.py
eouTools/numbers.py
eouTools/arithmetic_equations/__init__.py
eouTools/arithmetic_equations/integers.py
eouTools/arithmetic_equations/integrals.py
eouTools/benchmarking/__init__.py
eouTools/benchmarking/decorators.py
eouTools/eouMath/__init__.py
eouTools/eouMath/numbers.py
eouTools/eouMath/sorting.py
eouTools/morebytes/__init__.py
eouTools/morebytes/encryption.py
eouTools/rng/__init__.py
eouTools/rng/random.py
eouTools-0.1.1.dist-info/METADATA
eouTools-0.1.1.dist-info/WHEEL
eouTools-0.1.1.dist-info/top_level.txt
eouTools-0.1.1.dist-info/RECORD
