Metadata-Version: 2.1
Name: eouTools
Version: 0.1.1
Summary: eouTools adds new ease-of-use features to python!
Home-page: https://github.com/cornusandu/eouTools
Author: Sandu Bogdan
Author-email: bogdanelsandu@hotmail.com
Project-URL: Bug Tracker, https://github.com/cornusandu/eouTools/issues
Project-URL: GitHub Repository, https://github.com/cornusandu/eouTools
Classifier: Programming Language :: Python :: 3 :: Only
Classifier: Programming Language :: Python :: 3.10
Classifier: Programming Language :: Python :: 3.11
Classifier: Programming Language :: Python :: 3.12
Classifier: Programming Language :: Python :: 3.13
Classifier: Programming Language :: Python :: 3.14
Classifier: Operating System :: OS Independent
Requires-Python: >=3.10
Requires-Dist: Deprecated
Requires-Dist: numpy
